cc_country/__init__.py
cc_country/country.py
cc_country/exceptions.py
cc_country/data/countries.json
countryinfo_cloudcity-1.0.5.dist-info/METADATA
countryinfo_cloudcity-1.0.5.dist-info/WHEEL
countryinfo_cloudcity-1.0.5.dist-info/top_level.txt
countryinfo_cloudcity-1.0.5.dist-info/RECORD
