Metadata-Version: 2.1
Name: countryinfo-cloudcity
Version: 1.0.5
Summary: UNKNOWN
Home-page: https://gitlab.com/dqna/countryinfo-cloudcity
License: UNKNOWN
Platform: UNKNOWN
Requires-Python: >=3.9
Requires-Dist: pycountry
